fkrun/__init__.py
fkrun/__main__.py
fkrun-0.1.2.dist-info/LICENSE
fkrun-0.1.2.dist-info/METADATA
fkrun-0.1.2.dist-info/WHEEL
fkrun-0.1.2.dist-info/entry_points.txt
fkrun-0.1.2.dist-info/top_level.txt
fkrun-0.1.2.dist-info/RECORD
