Metadata-Version: 2.1
Name: fkrun
Version: 0.1.2
Summary: Code copier for multi experiments
Home-page: UNKNOWN
Author: Rudolfxx
Author-email: mayeoliver@163.com
License: UNKNOWN
Platform: UNKNOWN
Classifier: Programming Language :: Python :: 3
Classifier: License :: OSI Approved :: MIT License
Classifier: Operating System :: OS Independent
